{
  "name": "scene2",
  "maxRecursionLevel": 6,
  "antiAliasingFactor": 1,
  "renderRefarctions": true,
  "renderReflections": true,
  "camera": {
    "cameraPosition": {
      "x": 0.0,
      "y": 2.0,
      "z": 6.0
    },
    "centerPoint": {
      "x": 0.0,
      "y": 1.800992561958002,
      "z": 4.009925619580022
    },
    "towardsVec": {
      "x": 0.0,
      "y": -0.09950371902099893,
      "z": -0.9950371902099893
    },
    "upVec": {
      "x": 0.0,
      "y": 0.9950371902099893,
      "z": -0.09950371902099893
    },
    "rightVec": {
      "x": 1.0,
      "y": -0.0,
      "z": 0.0
    },
    "viewAngle": 2.0,
    "distanceToPlain": 2.0,
    "resX": 200.0,
    "resY": 200.0,
    "pixelRatio": 0.0
  },
  "ambient": {
    "x": 0.4,
    "y": 0.4,
    "z": 0.4
  },
  "backgroundColor": {
    "x": 0.0,
    "y": 0.5,
    "z": 1.0
  },
  "lightSources": [
    {
      "CLASSNAME": "edu.cg.scene.lightSources.DirectionalLight",
      "DATA": {
        "direction": {
          "x": 0.7071067811865475,
          "y": -0.7071067811865475,
          "z": 0.0
        },
        "intensity": {
          "x": 0.7,
          "y": 0.7,
          "z": 0.7
        }
      }
    }
  ],
  "surfaces": [
    {
      "shape": {
        "CLASSNAME": "edu.cg.scene.objects.Plain",
        "DATA": {
          "a": 0.0,
          "b": 1.0,
          "c": 0.0,
          "d": 1.0
        }
      },
      "material": {
        "Ka": {
          "x": 0.2,
          "y": 0.2,
          "z": 0.2
        },
        "Kd": {
          "x": 0.4,
          "y": 0.4,
          "z": 0.4
        },
        "Ks": {
          "x": 0.4,
          "y": 0.4,
          "z": 0.4
        },
        "reflectionIntensity": 0.2,
        "shininess": 10,
        "isTransparent": false,
        "refractionIntensity": 0.3,
        "refractionIndex": 1.5
      }
    },
    {
      "shape": {
        "CLASSNAME": "edu.cg.scene.objects.Sphere",
        "DATA": {
          "center": {
            "x": 0.0,
            "y": 0.0,
            "z": -0.0
          },
          "radius": 0.5
        }
      },
      "material": {
        "Ka": {
          "x": 0.2139529408379543,
          "y": 0.38728233872978834,
          "z": 0.15238755198333082
        },
        "Kd": {
          "x": 0.4279058816759086,
          "y": 0.7745646774595767,
          "z": 0.30477510396666163
        },
        "Ks": {
          "x": 0.49396654038821874,
          "y": 0.49396654038821874,
          "z": 0.49396654038821874
        },
        "reflectionIntensity": 0.0,
        "shininess": 10,
        "isTransparent": false,
        "refractionIntensity": 0.3,
        "refractionIndex": 1.5
      }
    },
    {
      "shape": {
        "CLASSNAME": "edu.cg.scene.objects.Sphere",
        "DATA": {
          "center": {
            "x": -1.0,
            "y": 0.0,
            "z": -1.0
          },
          "radius": 0.5
        }
      },
      "material": {
        "Ka": {
          "x": 0.32184395437182683,
          "y": 0.35878179877835653,
          "z": 0.11899206294619569
        },
        "Kd": {
          "x": 0.6436879087436537,
          "y": 0.7175635975567131,
          "z": 0.23798412589239137
        },
        "Ks": {
          "x": 1.0,
          "y": 1.0,
          "z": 1.0
        },
        "reflectionIntensity": 0.0,
        "shininess": 10,
        "isTransparent": false,
        "refractionIntensity": 0.3,
        "refractionIndex": 1.5
      }
    },
    {
      "shape": {
        "CLASSNAME": "edu.cg.scene.objects.Sphere",
        "DATA": {
          "center": {
            "x": 0.0,
            "y": 0.0,
            "z": -1.0
          },
          "radius": 0.5
        }
      },
      "material": {
        "Ka": {
          "x": 0.06702422257182034,
          "y": 0.0034505687815568065,
          "z": 0.4227887038830713
        },
        "Kd": {
          "x": 0.13404844514364067,
          "y": 0.006901137563113613,
          "z": 0.8455774077661427
        },
        "Ks": {
          "x": 0.6455997038520417,
          "y": 0.6455997038520417,
          "z": 0.6455997038520417
        },
        "reflectionIntensity": 0.0,
        "shininess": 10,
        "isTransparent": false,
        "refractionIntensity": 0.3,
        "refractionIndex": 1.5
      }
    },
    {
      "shape": {
        "CLASSNAME": "edu.cg.scene.objects.Sphere",
        "DATA": {
          "center": {
            "x": 1.0,
            "y": 0.0,
            "z": -1.0
          },
          "radius": 0.5
        }
      },
      "material": {
        "Ka": {
          "x": 0.05365208669810134,
          "y": 0.15599285396206009,
          "z": 0.4574775064629437
        },
        "Kd": {
          "x": 0.10730417339620268,
          "y": 0.31198570792412017,
          "z": 0.9149550129258874
        },
        "Ks": {
          "x": 0.37980571254711104,
          "y": 0.37980571254711104,
          "z": 0.37980571254711104
        },
        "reflectionIntensity": 0.0,
        "shininess": 10,
        "isTransparent": false,
        "refractionIntensity": 0.3,
        "refractionIndex": 1.5
      }
    },
    {
      "shape": {
        "CLASSNAME": "edu.cg.scene.objects.Sphere",
        "DATA": {
          "center": {
            "x": -2.0,
            "y": 0.0,
            "z": -2.0
          },
          "radius": 0.5
        }
      },
      "material": {
        "Ka": {
          "x": 0.22256015083025593,
          "y": 0.43478646406254035,
          "z": 0.028755953261779044
        },
        "Kd": {
          "x": 0.44512030166051186,
          "y": 0.8695729281250807,
          "z": 0.05751190652355809
        },
        "Ks": {
          "x": 0.6097259208707393,
          "y": 0.6097259208707393,
          "z": 0.6097259208707393
        },
        "reflectionIntensity": 0.0,
        "shininess": 10,
        "isTransparent": false,
        "refractionIntensity": 0.3,
        "refractionIndex": 1.5
      }
    },
    {
      "shape": {
        "CLASSNAME": "edu.cg.scene.objects.Sphere",
        "DATA": {
          "center": {
            "x": -1.0,
            "y": 0.0,
            "z": -2.0
          },
          "radius": 0.5
        }
      },
      "material": {
        "Ka": {
          "x": 0.4572470287648554,
          "y": 0.21013734591539773,
          "z": 0.25273786930701125
        },
        "Kd": {
          "x": 0.9144940575297108,
          "y": 0.42027469183079547,
          "z": 0.5054757386140225
        },
        "Ks": {
          "x": 0.8219181249506938,
          "y": 0.8219181249506938,
          "z": 0.8219181249506938
        },
        "reflectionIntensity": 0.0,
        "shininess": 10,
        "isTransparent": true,
        "refractionIntensity": 0.6258704639488807,
        "refractionIndex": 1.7593779903075635
      }
    },
    {
      "shape": {
        "CLASSNAME": "edu.cg.scene.objects.Sphere",
        "DATA": {
          "center": {
            "x": 0.0,
            "y": 0.0,
            "z": -2.0
          },
          "radius": 0.5
        }
      },
      "material": {
        "Ka": {
          "x": 0.41216431660057185,
          "y": 0.068660654940145,
          "z": 0.1555949878340926
        },
        "Kd": {
          "x": 0.8243286332011437,
          "y": 0.13732130988029,
          "z": 0.3111899756681852
        },
        "Ks": {
          "x": 0.8131582934348784,
          "y": 0.8131582934348784,
          "z": 0.8131582934348784
        },
        "reflectionIntensity": 0.0,
        "shininess": 10,
        "isTransparent": false,
        "refractionIntensity": 0.3,
        "refractionIndex": 1.5
      }
    },
    {
      "shape": {
        "CLASSNAME": "edu.cg.scene.objects.Sphere",
        "DATA": {
          "center": {
            "x": 1.0,
            "y": 0.0,
            "z": -2.0
          },
          "radius": 0.5
        }
      },
      "material": {
        "Ka": {
          "x": 0.3052669931159566,
          "y": 0.19595900702907293,
          "z": 0.17191765337170545
        },
        "Kd": {
          "x": 0.6105339862319132,
          "y": 0.39191801405814586,
          "z": 0.3438353067434109
        },
        "Ks": {
          "x": 0.9992464351170977,
          "y": 0.9992464351170977,
          "z": 0.9992464351170977
        },
        "reflectionIntensity": 0.0,
        "shininess": 10,
        "isTransparent": false,
        "refractionIntensity": 0.3,
        "refractionIndex": 1.5
      }
    },
    {
      "shape": {
        "CLASSNAME": "edu.cg.scene.objects.Sphere",
        "DATA": {
          "center": {
            "x": 2.0,
            "y": 0.0,
            "z": -2.0
          },
          "radius": 0.5
        }
      },
      "material": {
        "Ka": {
          "x": 0.4811300802603472,
          "y": 0.4907831358633223,
          "z": 0.4697645792271237
        },
        "Kd": {
          "x": 0.9622601605206944,
          "y": 0.9815662717266446,
          "z": 0.9395291584542474
        },
        "Ks": {
          "x": 1.0,
          "y": 1.0,
          "z": 1.0
        },
        "reflectionIntensity": 0.0,
        "shininess": 10,
        "isTransparent": true,
        "refractionIntensity": 0.7122680303288758,
        "refractionIndex": 1.7389706700281162
      }
    },
    {
      "shape": {
        "CLASSNAME": "edu.cg.scene.objects.Sphere",
        "DATA": {
          "center": {
            "x": -3.0,
            "y": 0.0,
            "z": -3.0
          },
          "radius": 0.5
        }
      },
      "material": {
        "Ka": {
          "x": 0.28203977005015024,
          "y": 0.4749778142785934,
          "z": 0.4826324748859694
        },
        "Kd": {
          "x": 0.5640795401003005,
          "y": 0.9499556285571868,
          "z": 0.9652649497719388
        },
        "Ks": {
          "x": 0.42458444586976707,
          "y": 0.42458444586976707,
          "z": 0.42458444586976707
        },
        "reflectionIntensity": 0.0,
        "shininess": 10,
        "isTransparent": true,
        "refractionIntensity": 1.0,
        "refractionIndex": 2.296990037364091
      }
    },
    {
      "shape": {
        "CLASSNAME": "edu.cg.scene.objects.Sphere",
        "DATA": {
          "center": {
            "x": -2.0,
            "y": 0.0,
            "z": -3.0
          },
          "radius": 0.5
        }
      },
      "material": {
        "Ka": {
          "x": 0.3167870955720062,
          "y": 0.46069536630746766,
          "z": 0.24782391022285644
        },
        "Kd": {
          "x": 0.6335741911440124,
          "y": 0.9213907326149353,
          "z": 0.49564782044571287
        },
        "Ks": {
          "x": 1.0,
          "y": 1.0,
          "z": 1.0
        },
        "reflectionIntensity": 0.0,
        "shininess": 10,
        "isTransparent": false,
        "refractionIntensity": 0.3,
        "refractionIndex": 1.5
      }
    },
    {
      "shape": {
        "CLASSNAME": "edu.cg.scene.objects.Sphere",
        "DATA": {
          "center": {
            "x": -1.0,
            "y": 0.0,
            "z": -3.0
          },
          "radius": 0.5
        }
      },
      "material": {
        "Ka": {
          "x": 0.4576321019050435,
          "y": 0.17326270431768787,
          "z": 0.44429379926261336
        },
        "Kd": {
          "x": 0.915264203810087,
          "y": 0.34652540863537573,
          "z": 0.8885875985252267
        },
        "Ks": {
          "x": 0.614986292095694,
          "y": 0.614986292095694,
          "z": 0.614986292095694
        },
        "reflectionIntensity": 0.0,
        "shininess": 10,
        "isTransparent": false,
        "refractionIntensity": 0.3,
        "refractionIndex": 1.5
      }
    },
    {
      "shape": {
        "CLASSNAME": "edu.cg.scene.objects.Sphere",
        "DATA": {
          "center": {
            "x": 0.0,
            "y": 0.0,
            "z": -3.0
          },
          "radius": 0.5
        }
      },
      "material": {
        "Ka": {
          "x": 0.1,
          "y": 0.1,
          "z": 0.1
        },
        "Kd": {
          "x": 0.1,
          "y": 0.1,
          "z": 0.1
        },
        "Ks": {
          "x": 0.1,
          "y": 0.1,
          "z": 0.1
        },
        "reflectionIntensity": 0.8,
        "shininess": 7,
        "isTransparent": true,
        "refractionIntensity": 0.2,
        "refractionIndex": 1.5
      }
    },
    {
      "shape": {
        "CLASSNAME": "edu.cg.scene.objects.Sphere",
        "DATA": {
          "center": {
            "x": 1.0,
            "y": 0.0,
            "z": -3.0
          },
          "radius": 0.5
        }
      },
      "material": {
        "Ka": {
          "x": 0.12365831566711155,
          "y": 0.44290029588347996,
          "z": 0.25149051197059513
        },
        "Kd": {
          "x": 0.2473166313342231,
          "y": 0.8858005917669599,
          "z": 0.5029810239411903
        },
        "Ks": {
          "x": 0.9871613934020187,
          "y": 0.9871613934020187,
          "z": 0.9871613934020187
        },
        "reflectionIntensity": 0.0,
        "shininess": 10,
        "isTransparent": false,
        "refractionIntensity": 0.3,
        "refractionIndex": 1.5
      }
    },
    {
      "shape": {
        "CLASSNAME": "edu.cg.scene.objects.Sphere",
        "DATA": {
          "center": {
            "x": 2.0,
            "y": 0.0,
            "z": -3.0
          },
          "radius": 0.5
        }
      },
      "material": {
        "Ka": {
          "x": 0.3149314779017046,
          "y": 0.2201217133006947,
          "z": 0.4693173140959627
        },
        "Kd": {
          "x": 0.6298629558034092,
          "y": 0.4402434266013894,
          "z": 0.9386346281919254
        },
        "Ks": {
          "x": 0.512428039235384,
          "y": 0.512428039235384,
          "z": 0.512428039235384
        },
        "reflectionIntensity": 0.0,
        "shininess": 10,
        "isTransparent": false,
        "refractionIntensity": 0.3,
        "refractionIndex": 1.5
      }
    },
    {
      "shape": {
        "CLASSNAME": "edu.cg.scene.objects.Sphere",
        "DATA": {
          "center": {
            "x": 3.0,
            "y": 0.0,
            "z": -3.0
          },
          "radius": 0.5
        }
      },
      "material": {
        "Ka": {
          "x": 0.15474868862241853,
          "y": 0.45927837285237033,
          "z": 0.4830268817211523
        },
        "Kd": {
          "x": 0.30949737724483706,
          "y": 0.9185567457047407,
          "z": 0.9660537634423046
        },
        "Ks": {
          "x": 0.915631562755534,
          "y": 0.915631562755534,
          "z": 0.915631562755534
        },
        "reflectionIntensity": 1.0,
        "shininess": 10,
        "isTransparent": false,
        "refractionIntensity": 0.3,
        "refractionIndex": 1.5
      }
    }
  ]
}